facturapi/__init__.py
facturapi/catalogs.py
facturapi/customers.py
facturapi/enums.py
facturapi/exceptions.py
facturapi/http.py
facturapi/invoices.py
facturapi/organizations.py
facturapi/products.py
facturapi/receipts.py
facturapi/retentions.py
facturapi/tools.py
facturapi/wrapper.py
facturapi_python-0.1.4.dist-info/METADATA
facturapi_python-0.1.4.dist-info/WHEEL
facturapi_python-0.1.4.dist-info/licenses/LICENSE
facturapi_python-0.1.4.dist-info/RECORD
