Metadata-Version: 2.1
Name: facturapi-python
Version: 0.1.4
Summary: Unofficial Facturapi.io Python client
Project-URL: Homepage, https://github.com/TI-Sin-Problemas/facturapi-python
Project-URL: Bug Tracker, https://github.com/TI-Sin-Problemas/facturapi-python/issues
Author-email: TI Sin Problemas <pypi@tisinproblemas.com>
License: MIT License
License-File: LICENSE
Keywords: cfdi,factura,mexico,sat
Classifier: Intended Audience :: Developers
Classifier: License :: OSI Approved :: MIT License
Classifier: Operating System :: OS Independent
Classifier: Programming Language :: Python :: 3
Classifier: Programming Language :: Python :: 3.5
Classifier: Programming Language :: Python :: 3.6
Classifier: Programming Language :: Python :: 3.7
Classifier: Programming Language :: Python :: 3.8
Classifier: Programming Language :: Python :: 3.9
Classifier: Programming Language :: Python :: 3.10
Requires-Python: >=3.5
Requires-Dist: requests<3,>=2.20
